ampeg/__init__.py
ampeg/_classes.py
ampeg/_exceptions.py
ampeg/_execution.py
ampeg/_helpers.py
ampeg/_scheduling.py
ampeg-0.2.0.dist-info/LICENSE.txt
ampeg-0.2.0.dist-info/METADATA
ampeg-0.2.0.dist-info/WHEEL
ampeg-0.2.0.dist-info/top_level.txt
ampeg-0.2.0.dist-info/RECORD
