Metadata-Version: 2.1
Name: ampeg
Version: 0.2.0
Summary: A simple and lightweight package for parallel computing
Home-page: https://github.com/sjpet/ampeg
Author: Stefan Peterson
Author-email: stefan.j.peterson@gmail.com
License: GPL-3.0
Download-URL: https://github.com/sjpet/ampeg/tarball/0.2.0
Keywords: parallellism multiprocessing async concurrent
Platform: UNKNOWN
Classifier: Development Status :: 4 - Beta
Classifier: Intended Audience :: Science/Research
Classifier: Intended Audience :: Developers
Classifier: License :: OSI Approved :: GNU General Public License (GPL)
Classifier: Programming Language :: Python :: 2.7
Classifier: Programming Language :: Python :: 3
Classifier: Programming Language :: Python :: 3.4
Classifier: Programming Language :: Python :: 3.5
Classifier: Programming Language :: Python :: 3.6
Classifier: Programming Language :: Python :: 3.7
Classifier: Programming Language :: Python :: 3.8
Classifier: Topic :: Utilities
Requires-Dist: six
Provides-Extra: dev
Requires-Dist: pytest ; extra == 'dev'
Requires-Dist: tox ; extra == 'dev'
